maketables/__init__.py
maketables/btable.py
maketables/dtable.py
maketables/etable.py
maketables/extractors.py
maketables/importdta.py
maketables/interactive.py
maketables/mtable.py
maketables/pystata_extractor.py
maketables/symbols.py
maketables-0.1.7.dist-info/licenses/LICENSE
maketables-0.1.7.dist-info/METADATA
maketables-0.1.7.dist-info/WHEEL
maketables-0.1.7.dist-info/top_level.txt
maketables-0.1.7.dist-info/RECORD
