Metadata-Version: 2.4
Name: maketables
Version: 0.1.7
Summary: A Python package for creating publication-ready tables from regression results (statsmodels, pyfixest, linearmodels), descriptive statistics, and balance tables with output to LaTeX, Word, and HTML/Great Tables
Author-email: Alexander Fischer <alexander-fischer1801@t-online.de>, Dirk Sliwka <dirk.sliwka@uni-koeln.de>
License: MIT
Project-URL: Homepage, https://github.com/py-econometrics/maketables
Project-URL: Documentation, https://py-econometrics.github.io/maketables/
Project-URL: Repository, https://github.com/py-econometrics/maketables
Project-URL: Issues, https://github.com/py-econometrics/maketables/issues
Keywords: tables,statistics,regression,econometrics,latex,publication,pyfixest,statsmodels
Classifier: Development Status :: 4 - Beta
Classifier: Intended Audience :: Science/Research
Classifier: License :: OSI Approved :: MIT License
Classifier: Programming Language :: Python :: 3
Classifier: Programming Language :: Python :: 3.8
Classifier: Programming Language :: Python :: 3.9
Classifier: Programming Language :: Python :: 3.10
Classifier: Programming Language :: Python :: 3.11
Classifier: Programming Language :: Python :: 3.12
Classifier: Topic :: Scientific/Engineering
Requires-Python: >=3.8
License-File: LICENSE
Requires-Dist: numpy>=1.20.0
Requires-Dist: pandas>=1.3.0
Requires-Dist: great-tables>=0.2.0
Requires-Dist: tabulate>=0.9.0
Requires-Dist: python-docx>=0.8.11
Requires-Dist: ipython>=7.0.0
Provides-Extra: dev
Requires-Dist: pytest>=7.0; extra == "dev"
Requires-Dist: pytest-cov>=4.0; extra == "dev"
Requires-Dist: syrupy>=4.0.0; extra == "dev"
Requires-Dist: pyfixest>=0.13.0; extra == "dev"
Requires-Dist: statsmodels>=0.13.0; extra == "dev"
Requires-Dist: linearmodels>=4.0; extra == "dev"
Requires-Dist: black>=22.0; extra == "dev"
Requires-Dist: flake8>=5.0; extra == "dev"
Requires-Dist: mypy>=1.0; extra == "dev"
Requires-Dist: pre-commit<5,>=4.3.0; extra == "dev"
Requires-Dist: quartodoc>=0.7.0; extra == "dev"
Provides-Extra: docs
Requires-Dist: sphinx>=5.0; extra == "docs"
Requires-Dist: sphinx-rtd-theme>=1.0; extra == "docs"
Requires-Dist: pyfixest>=0.13.0; extra == "docs"
Requires-Dist: statsmodels>=0.13.0; extra == "docs"
Requires-Dist: ipykernel<7,>=6.0.0; extra == "docs"
Requires-Dist: nbconvert>=7.0.0; extra == "docs"
Requires-Dist: pylatex<2,>=1.4.2; extra == "docs"
Requires-Dist: pyyaml<7,>=6.0.0; extra == "docs"
Provides-Extra: pystata
Requires-Dist: pystata>=0.0.1; extra == "pystata"
Requires-Dist: stata-setup>=0.1.0; extra == "pystata"
Provides-Extra: linearmodels
Requires-Dist: linearmodels>=4.0; extra == "linearmodels"
Requires-Dist: statsmodels>=0.13.0; extra == "linearmodels"
Provides-Extra: lifelines
Requires-Dist: lifelines>=0.27.0; extra == "lifelines"
Dynamic: license-file
